decoyable/__init__.py
decoyable/__main__.py
decoyable/cache.py
decoyable/database.py
decoyable/orchestrator.py
decoyable/secrets.py
decoyable/tasks.py
decoyable/ai/__init__.py
decoyable/ai/behavioral_anomaly.py
decoyable/ai/pattern_learner.py
decoyable/ai/predictive_threat.py
decoyable/api/__init__.py
decoyable/api/app.py
decoyable/api/honeypot_router.py
decoyable/api/service.py
decoyable/api/routers/attacks.py
decoyable/api/routers/health.py
decoyable/api/routers/metrics.py
decoyable/api/routers/scanning.py
decoyable/core/__init__.py
decoyable/core/cache_service.py
decoyable/core/cli.py
decoyable/core/cli_service.py
decoyable/core/config.py
decoyable/core/database_service.py
decoyable/core/honeypot_service.py
decoyable/core/logging.py
decoyable/core/main.py
decoyable/core/registry.py
decoyable/core/streaming_service.py
decoyable/core/task_definitions.py
decoyable/core/task_queue_service.py
decoyable/deception/__init__.py
decoyable/deception/adaptive_honeypot.py
decoyable/defense/__init__.py
decoyable/defense/adaptive_defense.py
decoyable/defense/analysis.py
decoyable/defense/honeypot.py
decoyable/defense/knowledge_base.py
decoyable/defense/llm_analysis.py
decoyable/defense/models.py
decoyable/defense/patterns.py
decoyable/llm/__init__.py
decoyable/llm/base.py
decoyable/llm/factory.py
decoyable/llm/model_router.py
decoyable/llm/ollama_client.py
decoyable/llm/phi3_local.py
decoyable/llm/router.py
decoyable/llm/providers/__init__.py
decoyable/llm/providers/anthropic.py
decoyable/llm/providers/anthropic_provider.py
decoyable/llm/providers/google.py
decoyable/llm/providers/openai.py
decoyable/llm/providers/openai_provider.py
decoyable/scanners/__init__.py
decoyable/scanners/deps.py
decoyable/scanners/deps_scanner.py
decoyable/scanners/interfaces.py
decoyable/scanners/sast.py
decoyable/scanners/sast_scanner.py
decoyable/scanners/secrets.py
decoyable/scanners/secrets_scanner.py
decoyable/scanners/service.py
decoyable/streaming/__init__.py
decoyable-1.2.2.dist-info/licenses/LICENSE
decoyable-1.2.2.dist-info/METADATA
decoyable-1.2.2.dist-info/WHEEL
decoyable-1.2.2.dist-info/entry_points.txt
decoyable-1.2.2.dist-info/top_level.txt
decoyable-1.2.2.dist-info/RECORD
