Metadata-Version: 2.4
Name: decoyable
Version: 1.2.2
Summary: Next-Generation Active Cyber Defense Platform - Find secrets, vulnerabilities, and attack patterns in your code
Author-email: Kolerr Lab <lab.kolerr@kolerr.com>
Maintainer-email: Kolerr Lab <lab.kolerr@kolerr.com>
License: MIT
Project-URL: Homepage, https://github.com/Kolerr-Lab/supper-decoyable
Project-URL: Documentation, https://github.com/Kolerr-Lab/supper-decoyable/wiki
Project-URL: Repository, https://github.com/Kolerr-Lab/supper-decoyable.git
Project-URL: Issues, https://github.com/Kolerr-Lab/supper-decoyable/issues
Project-URL: Changelog, https://github.com/Kolerr-Lab/supper-decoyable/blob/main/CHANGELOG.md
Keywords: security,scanning,vulnerabilities,secrets,SAST,cybersecurity,honeypot,AI,defense
Classifier: Development Status :: 5 - Production/Stable
Classifier: Intended Audience :: Developers
Classifier: Intended Audience :: Information Technology
Classifier: Intended Audience :: System Administrators
Classifier: License :: OSI Approved :: MIT License
Classifier: Operating System :: OS Independent
Classifier: Programming Language :: Python :: 3
Classifier: Programming Language :: Python :: 3.11
Classifier: Programming Language :: Python :: 3.12
Classifier: Topic :: Security
Classifier: Topic :: Software Development :: Quality Assurance
Classifier: Topic :: System :: Monitoring
Classifier: Topic :: System :: Networking :: Monitoring
Requires-Python: >=3.11
License-File: LICENSE
Requires-Dist: fastapi>=0.104.0
Requires-Dist: uvicorn[standard]>=0.24.0
Requires-Dist: pydantic>=2.5.0
Requires-Dist: python-multipart>=0.0.6
Requires-Dist: aiofiles>=23.2.1
Requires-Dist: jinja2>=3.1.2
Requires-Dist: python-jose[cryptography]>=3.3.0
Requires-Dist: passlib[bcrypt]>=1.7.4
Requires-Dist: python-decouple>=3.8
Requires-Dist: requests>=2.31.0
Requires-Dist: click>=8.1.7
Requires-Dist: rich>=13.7.0
Requires-Dist: pyyaml>=6.0.1
Requires-Dist: cryptography>=41.0.7
Requires-Dist: bandit>=1.7.6
Requires-Dist: safety>=2.3.5
Requires-Dist: pip-audit>=2.7.0
Requires-Dist: pytest>=7.4.3
Requires-Dist: pytest-cov>=4.1.0
Requires-Dist: pytest-asyncio>=0.21.1
Requires-Dist: httpx>=0.25.2
Requires-Dist: docker>=6.1.3
Requires-Dist: celery>=5.3.0
Requires-Dist: redis>=4.5.0
Requires-Dist: psutil>=5.9.0
Requires-Dist: aiokafka>=0.8.0
Requires-Dist: sqlalchemy>=2.0.0
Requires-Dist: alembic>=1.12.0
Requires-Dist: aiosqlite>=0.19.0
Requires-Dist: openai>=1.0.0
Requires-Dist: anthropic>=0.7.0
Requires-Dist: google-generativeai>=0.3.0
Dynamic: license-file
